LICENSE
README.md
setup.py
permaswap/__init__.py
permaswap/lp.py
permaswap/swap.py
permaswap.egg-info/PKG-INFO
permaswap.egg-info/SOURCES.txt
permaswap.egg-info/dependency_links.txt
permaswap.egg-info/requires.txt
permaswap.egg-info/top_level.txt