Metadata-Version: 2.1
Name: permaswap
Version: 0.1.3
Summary: Python wrappers for permaswap
Home-page: https://github.com/permaswap/permaswap.py
Download-URL: https://github.com/permaswap/permaswap.py/archive/refs/tags/v0.1.3.tar.gz
Author: haroldfinch2022
Author-email: e2d8nnhp8@gmail.com
License: MIT
Classifier: Programming Language :: Python :: 3
Classifier: Programming Language :: Python :: 2
Classifier: License :: OSI Approved :: MIT License
Classifier: Operating System :: OS Independent
License-File: LICENSE
